[
  {
    "tag": 0,
    "symbol": "histfig_entity_link_memberst",
    "inst_size": 16,
    "vtable_addr": "140f00218",
    "slot_0x0": "1400035f0",
    "slot_0x0_name": "FUN_1400035f0",
    "slot_0x100": "1400035f0",
    "slot_0x100_name": "FUN_1400035f0",
    "slot_0x18": "1406fb850",
    "slot_0x18_name": "FUN_1406fb850",
    "slot_0x10": "1406fb7f0",
    "slot_0x10_name": "FUN_1406fb7f0"
  },
  {
    "tag": 1,
    "symbol": "histfig_entity_link_former_memberst",
    "inst_size": 16,
    "vtable_addr": "140eff888",
    "slot_0x0": "140003c90",
    "slot_0x0_name": "FUN_140003c90",
    "slot_0x100": "1400037f0",
    "slot_0x100_name": "FUN_1400037f0",
    "slot_0x18": "1406fb850",
    "slot_0x18_name": "FUN_1406fb850",
    "slot_0x10": "1406fb7f0",
    "slot_0x10_name": "FUN_1406fb7f0"
  },
  {
    "tag": 2,
    "symbol": "histfig_entity_link_mercenaryst",
    "inst_size": 16,
    "vtable_addr": "140efffb8",
    "slot_0x0": "140003d20",
    "slot_0x0_name": "FUN_140003d20",
    "slot_0x100": "1400037f0",
    "slot_0x100_name": "FUN_1400037f0",
    "slot_0x18": "1406fb850",
    "slot_0x18_name": "FUN_1406fb850",
    "slot_0x10": "1406fb7f0",
    "slot_0x10_name": "FUN_1406fb7f0"
  },
  {
    "tag": 3,
    "symbol": "histfig_entity_link_former_mercenaryst",
    "inst_size": 16,
    "vtable_addr": "140efea78",
    "slot_0x0": "140003cb0",
    "slot_0x0_name": "FUN_140003cb0",
    "slot_0x100": "1400035c0",
    "slot_0x100_name": "FUN_1400035c0",
    "slot_0x18": "1406fb850",
    "slot_0x18_name": "FUN_1406fb850",
    "slot_0x10": "1406fb7f0",
    "slot_0x10_name": "FUN_1406fb7f0"
  },
  {
    "tag": 4,
    "symbol": "histfig_entity_link_slavest",
    "inst_size": 16,
    "vtable_addr": "140eff638",
    "slot_0x0": "1400043f0",
    "slot_0x0_name": "FUN_1400043f0",
    "slot_0x100": "1400037f0",
    "slot_0x100_name": "FUN_1400037f0",
    "slot_0x18": "1406fb850",
    "slot_0x18_name": "FUN_1406fb850",
    "slot_0x10": "1406fb7f0",
    "slot_0x10_name": "FUN_1406fb7f0"
  },
  {
    "tag": 5,
    "symbol": "histfig_entity_link_former_slavest",
    "inst_size": 16,
    "vtable_addr": "140f02cf8",
    "slot_0x0": "140004400",
    "slot_0x0_name": "FUN_140004400",
    "slot_0x100": "140490290",
    "slot_0x100_name": "FUN_140490290",
    "slot_0x18": "1406fb850",
    "slot_0x18_name": "FUN_1406fb850",
    "slot_0x10": "1406fb7f0",
    "slot_0x10_name": "FUN_1406fb7f0"
  },
  {
    "tag": 6,
    "symbol": "histfig_entity_link_prisonerst",
    "inst_size": 16,
    "vtable_addr": "140f01068",
    "slot_0x0": "140004460",
    "slot_0x0_name": "FUN_140004460",
    "slot_0x100": "14000c380",
    "slot_0x100_name": "_guard_check_icall",
    "slot_0x18": "1406fb850",
    "slot_0x18_name": "FUN_1406fb850",
    "slot_0x10": "1406fb7f0",
    "slot_0x10_name": "FUN_1406fb7f0"
  },
  {
    "tag": 7,
    "symbol": "histfig_entity_link_former_prisonerst",
    "inst_size": 16,
    "vtable_addr": "140f029b8",
    "slot_0x0": "140003cc0",
    "slot_0x0_name": "FUN_140003cc0",
    "slot_0x100": "1400035c0",
    "slot_0x100_name": "FUN_1400035c0",
    "slot_0x18": "1406fb850",
    "slot_0x18_name": "FUN_1406fb850",
    "slot_0x10": "1406fb7f0",
    "slot_0x10_name": "FUN_1406fb7f0"
  },
  {
    "tag": 8,
    "symbol": "histfig_entity_link_enemyst",
    "inst_size": 16,
    "vtable_addr": "140f00278",
    "slot_0x0": "140004100",
    "slot_0x0_name": "FUN_140004100",
    "slot_0x100": "140082ba0",
    "slot_0x100_name": "FUN_140082ba0",
    "slot_0x18": "1406fb850",
    "slot_0x18_name": "FUN_1406fb850",
    "slot_0x10": "1406fb7f0",
    "slot_0x10_name": "FUN_1406fb7f0"
  },
  {
    "tag": 9,
    "symbol": "histfig_entity_link_criminalst",
    "inst_size": 16,
    "vtable_addr": "140efec78",
    "slot_0x0": "140003ea0",
    "slot_0x0_name": "FUN_140003ea0",
    "slot_0x100": "1400037f0",
    "slot_0x100_name": "FUN_1400037f0",
    "slot_0x18": "1406fb850",
    "slot_0x18_name": "FUN_1406fb850",
    "slot_0x10": "1406fb7f0",
    "slot_0x10_name": "FUN_1406fb7f0"
  },
  {
    "tag": 10,
    "symbol": "histfig_entity_link_positionst",
    "inst_size": 24,
    "vtable_addr": "140f00158",
    "slot_0x0": "140003a80",
    "slot_0x0_name": "FUN_140003a80",
    "slot_0x100": "1400035c0",
    "slot_0x100_name": "FUN_1400035c0",
    "slot_0x18": "1406fb950",
    "slot_0x18_name": "FUN_1406fb950",
    "slot_0x10": "1406fb8c0",
    "slot_0x10_name": "FUN_1406fb8c0"
  },
  {
    "tag": 11,
    "symbol": "histfig_entity_link_former_positionst",
    "inst_size": null,
    "vtable_addr": "140f00448",
    "slot_0x0": "140003af0",
    "slot_0x0_name": "FUN_140003af0",
    "slot_0x100": "1400035c0",
    "slot_0x100_name": "FUN_1400035c0",
    "slot_0x18": "1406fba90",
    "slot_0x18_name": "FUN_1406fba90",
    "slot_0x10": "1406fb9f0",
    "slot_0x10_name": "FUN_1406fb9f0"
  },
  {
    "tag": 12,
    "symbol": "histfig_entity_link_position_claimst",
    "inst_size": 24,
    "vtable_addr": "140f02a18",
    "slot_0x0": "140003c30",
    "slot_0x0_name": "FUN_140003c30",
    "slot_0x100": "1400037f0",
    "slot_0x100_name": "FUN_1400037f0",
    "slot_0x18": "1406fb950",
    "slot_0x18_name": "FUN_1406fb950",
    "slot_0x10": "1406fb8c0",
    "slot_0x10_name": "FUN_1406fb8c0"
  },
  {
    "tag": 13,
    "symbol": "histfig_entity_link_squadst",
    "inst_size": null,
    "vtable_addr": "140efee18",
    "slot_0x0": "140015f30",
    "slot_0x0_name": "FUN_140015f30",
    "slot_0x100": "1400037f0",
    "slot_0x100_name": "FUN_1400037f0",
    "slot_0x18": "1406fba90",
    "slot_0x18_name": "FUN_1406fba90",
    "slot_0x10": "1406fb9f0",
    "slot_0x10_name": "FUN_1406fb9f0"
  },
  {
    "tag": 14,
    "symbol": "histfig_entity_link_former_squadst",
    "inst_size": null,
    "vtable_addr": "140efead8",
    "slot_0x0": "140017b90",
    "slot_0x0_name": "FUN_140017b90",
    "slot_0x100": "1400037f0",
    "slot_0x100_name": "FUN_1400037f0",
    "slot_0x18": "1406fba90",
    "slot_0x18_name": "FUN_1406fba90",
    "slot_0x10": "1406fb9f0",
    "slot_0x10_name": "FUN_1406fb9f0"
  },
  {
    "tag": 15,
    "symbol": "histfig_entity_link_occupationst",
    "inst_size": 24,
    "vtable_addr": "140f02358",
    "slot_0x0": "140015ad0",
    "slot_0x0_name": "FUN_140015ad0",
    "slot_0x100": "1400037f0",
    "slot_0x100_name": "FUN_1400037f0",
    "slot_0x18": "1406fb950",
    "slot_0x18_name": "FUN_1406fb950",
    "slot_0x10": "1406fb8c0",
    "slot_0x10_name": "FUN_1406fb8c0"
  },
  {
    "tag": 16,
    "symbol": "histfig_entity_link_former_occupationst",
    "inst_size": null,
    "vtable_addr": "140effec8",
    "slot_0x0": "1400164f0",
    "slot_0x0_name": "FUN_1400164f0",
    "slot_0x100": "1406fb7f0",
    "slot_0x100_name": "FUN_1406fb7f0",
    "slot_0x18": "1406fba90",
    "slot_0x18_name": "FUN_1406fba90",
    "slot_0x10": "1406fb9f0",
    "slot_0x10_name": "FUN_1406fb9f0"
  }
]
